README.md
setup.py
xl_tensorflow/__init__.py
xl_tensorflow/debug_free.py
xl_tensorflow.egg-info/PKG-INFO
xl_tensorflow.egg-info/SOURCES.txt
xl_tensorflow.egg-info/dependency_links.txt
xl_tensorflow.egg-info/top_level.txt
xl_tensorflow/benchmark/__init__.py
xl_tensorflow/datasets/__init__.py
xl_tensorflow/datasets/tfrecord/__init__.py
xl_tensorflow/datasets/tfrecord/create_coco_tfrecord.py
xl_tensorflow/datasets/tfrecord/create_coco_tfrecord_test.py
xl_tensorflow/datasets/tfrecord/create_pascal_tfrecord.py
xl_tensorflow/datasets/tfrecord/create_pascal_tfrecord_test.py
xl_tensorflow/datasets/tfrecord/create_voc_tfrecord.py
xl_tensorflow/datasets/tfrecord/label_map_util.py
xl_tensorflow/datasets/tfrecord/tfrecord_util.py
xl_tensorflow/examples/__init__.py
xl_tensorflow/layers/__init__.py
xl_tensorflow/layers/actication.py
xl_tensorflow/layers/conv.py
xl_tensorflow/layers/initializers.py
xl_tensorflow/layers/normalization.py
xl_tensorflow/metrics/__init__.py
xl_tensorflow/metrics/detection.py
xl_tensorflow/metrics/general.py
xl_tensorflow/metrics/rafaelpadilla/BoundingBox.py
xl_tensorflow/metrics/rafaelpadilla/BoundingBoxes.py
xl_tensorflow/metrics/rafaelpadilla/Evaluator.py
xl_tensorflow/metrics/rafaelpadilla/__init__.py
xl_tensorflow/metrics/rafaelpadilla/pascalvoc.py
xl_tensorflow/metrics/rafaelpadilla/utils.py
xl_tensorflow/models/__init__.py
xl_tensorflow/models/vision/__init__.py
xl_tensorflow/models/vision/classification/__init__.py
xl_tensorflow/models/vision/classification/darknet.py
xl_tensorflow/models/vision/classification/efficientnet.py
xl_tensorflow/models/vision/classification/mobilenet_v3.py
xl_tensorflow/models/vision/classification/utils/__init__.py
xl_tensorflow/models/vision/classification/utils/autoaug.py
xl_tensorflow/models/vision/classification/utils/deploy.py
xl_tensorflow/models/vision/classification/utils/fintune.py
xl_tensorflow/models/vision/classification/utils/my_aug_ops.py
xl_tensorflow/models/vision/classification/utils/preprocessing.py
xl_tensorflow/models/vision/classification/utils/pretrained_model.py
xl_tensorflow/models/vision/classification/utils/serving_api.py
